README.md
setup.py
webspinner/__init__.py
webspinner/__version__.py
webspinner/pautils.py
webspinner.egg-info/PKG-INFO
webspinner.egg-info/SOURCES.txt
webspinner.egg-info/dependency_links.txt
webspinner.egg-info/requires.txt
webspinner.egg-info/top_level.txt
webspinner/connect/__init__.py
webspinner/connect/aws.py
webspinner/connect/pgres.py