Metadata-Version: 2.1
Name: webspinner
Version: 1.1.0
Summary: Python utilities for working with various dsgrid data sources
Home-page: https://github.com/dsgrid/webspinner
Author: Elaine T. Hale
Author-email: elaine.hale@nrel.gov
License: BSD-3
Platform: UNKNOWN
Classifier: Intended Audience :: Science/Research
Classifier: License :: OSI Approved :: BSD License
Classifier: Natural Language :: English
Classifier: Programming Language :: Python
Requires-Python: >=3.6
Provides-Extra: aws
Provides-Extra: pgres
Provides-Extra: parquet
Provides-Extra: dev
